pybel_jupyter/__init__.py
pybel_jupyter-0.3.0.dist-info/LICENSE
pybel_jupyter-0.3.0.dist-info/METADATA
pybel_jupyter-0.3.0.dist-info/WHEEL
pybel_jupyter-0.3.0.dist-info/top_level.txt
pybel_jupyter-0.3.0.dist-info/RECORD
