Metadata-Version: 2.1
Name: pybel-jupyter
Version: 0.3.0
Summary: A PyBEL extension for Jupyter notebooks
Home-page: https://github.com/pybel/pybel-jupyter
Author: Charles Tapley Hoyt
Author-email: cthoyt@gmail.com
Maintainer: Charles Tapley Hoyt
Maintainer-email: cthoyt@gmail.com
License: MIT
Download-URL: https://github.com/pybel/pybel-jupyter/releases
Project-URL: Bug Tracker, https://github.com/pybel/pybel-jupyter/issues
Project-URL: Source Code, https://github.com/pybel/pybel-jupyter
Project-URL: Documentation, https://pybel-jupyter.readthedocs.io
Keywords: Biological Expression Language,BEL,Domain Specific Language,DSL,Systems Biology,Networks Biology
Platform: UNKNOWN
Classifier: Development Status :: 5 - Production/Stable
Classifier: Environment :: Console
Classifier: Intended Audience :: Developers
Classifier: Intended Audience :: Science/Research
Classifier: License :: OSI Approved :: MIT License
Classifier: Operating System :: OS Independent
Classifier: Programming Language :: Python
Classifier: Programming Language :: Python :: 3.7
Classifier: Programming Language :: Python :: 3.6
Classifier: Programming Language :: Python :: 3.5
Classifier: Programming Language :: Python :: 3 :: Only
Classifier: Topic :: Scientific/Engineering :: Bio-Informatics
Classifier: Topic :: Scientific/Engineering :: Chemistry
Requires-Python: >=3.5
Requires-Dist: pybel (>=0.14.7)
Requires-Dist: jinja2
Requires-Dist: ipython
Provides-Extra: docs
Requires-Dist: sphinx ; extra == 'docs'
Requires-Dist: sphinx-rtd-theme ; extra == 'docs'
Requires-Dist: sphinx-click ; extra == 'docs'
Requires-Dist: sphinx-autodoc-typehints ; extra == 'docs'
